inoagent/__init__.py
inoagent/dto.py
inoagent/exceptions.py
inoagent/sync_mode.py
inoagent/utils.py
inoagent_registry-1.0.2.dist-info/LICENSE
inoagent_registry-1.0.2.dist-info/METADATA
inoagent_registry-1.0.2.dist-info/WHEEL
inoagent_registry-1.0.2.dist-info/top_level.txt
inoagent_registry-1.0.2.dist-info/RECORD
